create_rag/__init__.py
create_rag/cli.py
create_rag-0.1.1.dist-info/METADATA
create_rag-0.1.1.dist-info/WHEEL
create_rag-0.1.1.dist-info/entry_points.txt
create_rag-0.1.1.dist-info/top_level.txt
create_rag-0.1.1.dist-info/RECORD
