Metadata-Version: 2.4
Name: create-rag
Version: 0.1.1
Summary: CLI tool to scaffold RAG projects
Author: Your Name
